iptables_tools/__init__.py
iptables_tools/cli.py
iptables_tools/controls/exceptions.py
iptables_tools/controls/iptables.py
iptables_tools/controls/utils.py
iptables_tools/systemd/iptables-tools.service
iptables_tools/templates/default.toml
iptables_tools-0.1.0.dist-info/LICENSE
iptables_tools-0.1.0.dist-info/METADATA
iptables_tools-0.1.0.dist-info/WHEEL
iptables_tools-0.1.0.dist-info/entry_points.txt
iptables_tools-0.1.0.dist-info/RECORD
