Metadata-Version: 2.1
Name: iptables-tools
Version: 0.1.0
Summary: Manipule as regras do iptables de forma simples.
Author: Edgar Reis
Author-email: edgar_reis_silva@hotmail.com
Requires-Python: >=3.10,<4.0
Classifier: Programming Language :: Python :: 3
Classifier: Programming Language :: Python :: 3.10
Classifier: Programming Language :: Python :: 3.11
Classifier: Programming Language :: Python :: 3.12
Requires-Dist: toml (>=0.10.2,<0.11.0)
